imdb/__init__.py
imdb/__main__.py
imdb/api.py
imdb/imdb.py
tdm_imdb_get_rating-0.1.1.dist-info/LICENSE
tdm_imdb_get_rating-0.1.1.dist-info/METADATA
tdm_imdb_get_rating-0.1.1.dist-info/WHEEL
tdm_imdb_get_rating-0.1.1.dist-info/entry_points.txt
tdm_imdb_get_rating-0.1.1.dist-info/top_level.txt
tdm_imdb_get_rating-0.1.1.dist-info/RECORD
